dkube_cli/__init__.py
dkube_cli/cli.py
dkube_cli/dkube_cli.py
dkube_cli/commands/__init__.py
dkube_cli/commands/datum.py
dkube_cli/commands/ide.py
dkube_cli/commands/projects.py
dkube_cli/commands/runs.py
dkube_cli-0.1.1.dist-info/METADATA
dkube_cli-0.1.1.dist-info/WHEEL
dkube_cli-0.1.1.dist-info/entry_points.txt
dkube_cli-0.1.1.dist-info/top_level.txt
dkube_cli-0.1.1.dist-info/RECORD
